boxdetect/__init__.py
boxdetect/config.py
boxdetect/img_proc.py
boxdetect/pipelines.py
boxdetect/rect_proc.py
boxdetect-1.0.2.dist-info/LICENSE
boxdetect-1.0.2.dist-info/METADATA
boxdetect-1.0.2.dist-info/WHEEL
boxdetect-1.0.2.dist-info/top_level.txt
boxdetect-1.0.2.dist-info/RECORD
