Metadata-Version: 2.1
Name: boxdetect
Version: 1.0.2
Summary: boxdetect is a Python package based on OpenCV which allows you to easily detect rectangular shapes like characters boxes on scanned forms.
Home-page: http://github.com/karolzak/boxdetect
Author: Karol Zak
Author-email: karol.zak@hotmail.com
License: MIT
Classifier: Development Status :: 5 - Production/Stable
Classifier: Intended Audience :: Developers
Classifier: Intended Audience :: Education
Classifier: Intended Audience :: Science/Research
Classifier: License :: OSI Approved :: MIT License
Classifier: Programming Language :: Python :: 3.7
Classifier: Programming Language :: Python :: 3.8
Classifier: Programming Language :: Python :: 3.9
Classifier: Programming Language :: Python :: 3.10
Classifier: Topic :: Software Development :: Libraries
Classifier: Topic :: Software Development :: Libraries :: Python Modules
License-File: LICENSE
